lolexport/__init__.py
lolexport/__main__.py
lolexport/cli.py
lolexport/common.py
lolexport/export.py
lolexport/log.py
lolexport/merge.py
lolexport/parse.py
lolexport/py.typed
lolexport-0.1.3.dist-info/LICENSE
lolexport-0.1.3.dist-info/METADATA
lolexport-0.1.3.dist-info/WHEEL
lolexport-0.1.3.dist-info/entry_points.txt
lolexport-0.1.3.dist-info/top_level.txt
lolexport-0.1.3.dist-info/RECORD
