Metadata-Version: 2.1
Name: lolexport
Version: 0.1.3
Summary: Exports League of Legends Match History data using the RiotGames API
Home-page: https://github.com/seanbreckenridge/lolexport
Author: Sean Breckenridge
Author-email: seanbrecke@gmail.com
License: MIT
Keywords: api
Classifier: License :: OSI Approved :: MIT License
Classifier: Programming Language :: Python
Classifier: Programming Language :: Python :: 3
Classifier: Programming Language :: Python :: 3.7
Classifier: Programming Language :: Python :: 3.8
Classifier: Programming Language :: Python :: 3.9
Classifier: Programming Language :: Python :: 3.10
License-File: LICENSE
Requires-Dist: click (>=8.0)
Requires-Dist: logzero
Requires-Dist: riotwatcher
Requires-Dist: backoff
Requires-Dist: IPython
Provides-Extra: testing
Requires-Dist: mypy ; extra == 'testing'
Requires-Dist: flake8 ; extra == 'testing'
